{
  "timestamp": "2026-06-18 14:04:44",
  "model": "V-JEPA 2 ViT-L/16 (facebookresearch/jepa), frozen",
  "evaluation": "LOSO per dataset \u2014 GroupKFold(n_splits=n_subjects)",
  "probe": "LogisticRegression (C=1.0, class_weight=balanced, fixed)",
  "rationale": {
    "loso": "Matches Care-PD paper within-dataset evaluation protocol.",
    "per_dataset": "Avoids conflating within- and cross-dataset generalisation.",
    "fixed_C": "C=1.0 fixed \u2014 see videomae_loso.py for full rationale."
  },
  "datasets": {
    "PD-GaM": {
      "dataset": "PD-GaM",
      "n_subjects": 30,
      "n_clips": 2401,
      "n_folds": 30,
      "updrs_dist": {
        "0": 812,
        "1": 861,
        "2": 692,
        "3": 36
      },
      "folds": [
        {
          "fold": 1,
          "test_subject": "057",
          "n_train_clips": 2233,
          "n_test_clips": 168,
          "n_test_walks": 56,
          "f1_macro_03": 0.6112,
          "f1_macro_02": 0.6112,
          "f1_weighted": 0.6583,
          "accuracy": 0.6964,
          "mae": 0.4286,
          "qwk": 0.7358
        },
        {
          "fold": 2,
          "test_subject": "042",
          "n_train_clips": 2290,
          "n_test_clips": 111,
          "n_test_walks": 48,
          "f1_macro_03": 0.3938,
          "f1_macro_02": 0.3938,
          "f1_weighted": 0.4425,
          "accuracy": 0.4583,
          "mae": 0.7083,
          "qwk": 0.5078
        },
        {
          "fold": 3,
          "test_subject": "004",
          "n_train_clips": 2291,
          "n_test_clips": 110,
          "n_test_walks": 66,
          "f1_macro_03": 0.4708,
          "f1_macro_02": 0.4611,
          "f1_weighted": 0.4698,
          "accuracy": 0.5152,
          "mae": 0.5152,
          "qwk": 0.7817
        },
        {
          "fold": 4,
          "test_subject": "026",
          "n_train_clips": 2293,
          "n_test_clips": 108,
          "n_test_walks": 56,
          "f1_macro_03": 0.6159,
          "f1_macro_02": 0.6159,
          "f1_weighted": 0.62,
          "accuracy": 0.625,
          "mae": 0.3214,
          "qwk": 0.6971
        },
        {
          "fold": 5,
          "test_subject": "019",
          "n_train_clips": 2293,
          "n_test_clips": 108,
          "n_test_walks": 58,
          "f1_macro_03": 0.7305,
          "f1_macro_02": 0.654,
          "f1_weighted": 0.7257,
          "accuracy": 0.7241,
          "mae": 0.3621,
          "qwk": 0.8429
        },
        {
          "fold": 6,
          "test_subject": "023",
          "n_train_clips": 2304,
          "n_test_clips": 97,
          "n_test_walks": 56,
          "f1_macro_03": 0.454,
          "f1_macro_02": 0.6809,
          "f1_weighted": 0.8012,
          "accuracy": 0.8036,
          "mae": 0.1607,
          "qwk": 0.3942
        },
        {
          "fold": 7,
          "test_subject": "062",
          "n_train_clips": 2305,
          "n_test_clips": 96,
          "n_test_walks": 52,
          "f1_macro_03": 0.7174,
          "f1_macro_02": 0.7174,
          "f1_weighted": 0.7997,
          "accuracy": 0.7885,
          "mae": 0.3077,
          "qwk": 0.8156
        },
        {
          "fold": 8,
          "test_subject": "044",
          "n_train_clips": 2310,
          "n_test_clips": 91,
          "n_test_walks": 64,
          "f1_macro_03": 0.4715,
          "f1_macro_02": 0.7073,
          "f1_weighted": 0.6998,
          "accuracy": 0.625,
          "mae": 0.375,
          "qwk": 0.4667
        },
        {
          "fold": 9,
          "test_subject": "038",
          "n_train_clips": 2312,
          "n_test_clips": 89,
          "n_test_walks": 49,
          "f1_macro_03": 0.5336,
          "f1_macro_02": 0.5336,
          "f1_weighted": 0.6072,
          "accuracy": 0.5918,
          "mae": 0.3265,
          "qwk": 0.6183
        },
        {
          "fold": 10,
          "test_subject": "059",
          "n_train_clips": 2313,
          "n_test_clips": 88,
          "n_test_walks": 58,
          "f1_macro_03": 0.6944,
          "f1_macro_02": 0.6944,
          "f1_weighted": 0.6979,
          "accuracy": 0.6897,
          "mae": 0.4138,
          "qwk": 0.5385
        },
        {
          "fold": 11,
          "test_subject": "030",
          "n_train_clips": 2313,
          "n_test_clips": 88,
          "n_test_walks": 64,
          "f1_macro_03": 0.2666,
          "f1_macro_02": 0.3999,
          "f1_weighted": 0.5791,
          "accuracy": 0.4688,
          "mae": 0.375,
          "qwk": 0.1028
        },
        {
          "fold": 12,
          "test_subject": "027",
          "n_train_clips": 2318,
          "n_test_clips": 83,
          "n_test_walks": 56,
          "f1_macro_03": 0.5747,
          "f1_macro_02": 0.5747,
          "f1_weighted": 0.5808,
          "accuracy": 0.5893,
          "mae": 0.4107,
          "qwk": 0.4651
        },
        {
          "fold": 13,
          "test_subject": "065",
          "n_train_clips": 2322,
          "n_test_clips": 79,
          "n_test_walks": 56,
          "f1_macro_03": 0.5251,
          "f1_macro_02": 0.5251,
          "f1_weighted": 0.504,
          "accuracy": 0.5179,
          "mae": 0.5179,
          "qwk": 0.4755
        },
        {
          "fold": 14,
          "test_subject": "047",
          "n_train_clips": 2322,
          "n_test_clips": 79,
          "n_test_walks": 56,
          "f1_macro_03": 0.4311,
          "f1_macro_02": 0.6467,
          "f1_weighted": 0.6639,
          "accuracy": 0.6786,
          "mae": 0.3214,
          "qwk": 0.3571
        },
        {
          "fold": 15,
          "test_subject": "049",
          "n_train_clips": 2329,
          "n_test_clips": 72,
          "n_test_walks": 56,
          "f1_macro_03": 0.4928,
          "f1_macro_02": 0.7391,
          "f1_weighted": 0.7391,
          "accuracy": 0.75,
          "mae": 0.1607,
          "qwk": 0.6786
        },
        {
          "fold": 16,
          "test_subject": "008",
          "n_train_clips": 2329,
          "n_test_clips": 72,
          "n_test_walks": 56,
          "f1_macro_03": 0.4476,
          "f1_macro_02": 0.4476,
          "f1_weighted": 0.4616,
          "accuracy": 0.4643,
          "mae": 0.5536,
          "qwk": 0.3265
        },
        {
          "fold": 17,
          "test_subject": "007",
          "n_train_clips": 2330,
          "n_test_clips": 71,
          "n_test_walks": 56,
          "f1_macro_03": 0.2476,
          "f1_macro_02": 0.3714,
          "f1_weighted": 0.5347,
          "accuracy": 0.3929,
          "mae": 0.6786,
          "qwk": 0.2473
        },
        {
          "fold": 18,
          "test_subject": "036",
          "n_train_clips": 2333,
          "n_test_clips": 68,
          "n_test_walks": 60,
          "f1_macro_03": 0.7,
          "f1_macro_02": 0.7,
          "f1_weighted": 0.7333,
          "accuracy": 0.7333,
          "mae": 0.2833,
          "qwk": 0.4138
        },
        {
          "fold": 19,
          "test_subject": "022",
          "n_train_clips": 2333,
          "n_test_clips": 68,
          "n_test_walks": 60,
          "f1_macro_03": 0.3903,
          "f1_macro_02": 0.3903,
          "f1_weighted": 0.5637,
          "accuracy": 0.5833,
          "mae": 0.3167,
          "qwk": 0.5638
        },
        {
          "fold": 20,
          "test_subject": "066",
          "n_train_clips": 2336,
          "n_test_clips": 65,
          "n_test_walks": 56,
          "f1_macro_03": 0.38,
          "f1_macro_02": 0.38,
          "f1_weighted": 0.4891,
          "accuracy": 0.5714,
          "mae": 0.4464,
          "qwk": 0.2358
        },
        {
          "fold": 21,
          "test_subject": "039",
          "n_train_clips": 2336,
          "n_test_clips": 65,
          "n_test_walks": 57,
          "f1_macro_03": 0.3861,
          "f1_macro_02": 0.3861,
          "f1_weighted": 0.3525,
          "accuracy": 0.386,
          "mae": 0.6491,
          "qwk": 0.4989
        },
        {
          "fold": 22,
          "test_subject": "024",
          "n_train_clips": 2338,
          "n_test_clips": 63,
          "n_test_walks": 56,
          "f1_macro_03": 0.4275,
          "f1_macro_02": 0.4275,
          "f1_weighted": 0.5798,
          "accuracy": 0.6429,
          "mae": 0.4464,
          "qwk": 0.5675
        },
        {
          "fold": 23,
          "test_subject": "009",
          "n_train_clips": 2341,
          "n_test_clips": 60,
          "n_test_walks": 56,
          "f1_macro_03": 0.6536,
          "f1_macro_02": 0.6536,
          "f1_weighted": 0.8348,
          "accuracy": 0.8393,
          "mae": 0.0893,
          "qwk": 0.6535
        },
        {
          "fold": 24,
          "test_subject": "011",
          "n_train_clips": 2341,
          "n_test_clips": 60,
          "n_test_walks": 56,
          "f1_macro_03": 0.439,
          "f1_macro_02": 0.439,
          "f1_weighted": 0.6603,
          "accuracy": 0.6964,
          "mae": 0.3393,
          "qwk": 0.1688
        },
        {
          "fold": 25,
          "test_subject": "003",
          "n_train_clips": 2342,
          "n_test_clips": 59,
          "n_test_walks": 56,
          "f1_macro_03": 0.3611,
          "f1_macro_02": 0.3611,
          "f1_weighted": 0.6071,
          "accuracy": 0.6786,
          "mae": 0.2321,
          "qwk": 0.6224
        },
        {
          "fold": 26,
          "test_subject": "006",
          "n_train_clips": 2342,
          "n_test_clips": 59,
          "n_test_walks": 56,
          "f1_macro_03": 0.6551,
          "f1_macro_02": 0.6551,
          "f1_weighted": 0.7062,
          "accuracy": 0.7321,
          "mae": 0.375,
          "qwk": 0.54
        },
        {
          "fold": 27,
          "test_subject": "037",
          "n_train_clips": 2345,
          "n_test_clips": 56,
          "n_test_walks": 56,
          "f1_macro_03": 0.3913,
          "f1_macro_02": 0.7826,
          "f1_weighted": 0.7826,
          "accuracy": 0.6429,
          "mae": 0.3929,
          "qwk": 0.0
        },
        {
          "fold": 28,
          "test_subject": "012",
          "n_train_clips": 2345,
          "n_test_clips": 56,
          "n_test_walks": 56,
          "f1_macro_03": 0.406,
          "f1_macro_02": 0.609,
          "f1_weighted": 0.7051,
          "accuracy": 0.7143,
          "mae": 0.3036,
          "qwk": 0.2119
        },
        {
          "fold": 29,
          "test_subject": "005",
          "n_train_clips": 2345,
          "n_test_clips": 56,
          "n_test_walks": 56,
          "f1_macro_03": 0.4093,
          "f1_macro_02": 0.614,
          "f1_weighted": 0.8954,
          "accuracy": 0.8929,
          "mae": 0.0536,
          "qwk": 0.7
        },
        {
          "fold": 30,
          "test_subject": "001",
          "n_train_clips": 2345,
          "n_test_clips": 56,
          "n_test_walks": 56,
          "f1_macro_03": 0.44,
          "f1_macro_02": 0.44,
          "f1_weighted": 0.6914,
          "accuracy": 0.7857,
          "mae": 0.1607,
          "qwk": 0.4375
        }
      ],
      "summary": {
        "f1_macro_03_mean": 0.6411,
        "f1_macro_03_std": 0.1287,
        "f1_macro_02_mean": 0.6159,
        "f1_macro_02_std": 0.1311,
        "f1_weighted_mean": 0.6406,
        "f1_weighted_std": 0.1258,
        "accuracy_mean": 0.6418,
        "accuracy_std": 0.1278,
        "mae_mean": 0.3671,
        "mae_std": 0.1569,
        "qwk_mean": 0.6557,
        "qwk_std": 0.2108,
        "spearman_mean": 0.6625,
        "spearman_std": null
      }
    },
    "BMClab": {
      "dataset": "BMClab",
      "n_subjects": 23,
      "n_clips": 893,
      "n_folds": 23,
      "updrs_dist": {
        "0": 341,
        "1": 277,
        "2": 275
      },
      "folds": [
        {
          "fold": 1,
          "test_subject": "SUB07",
          "n_train_clips": 806,
          "n_test_clips": 87,
          "n_test_walks": 33,
          "f1_macro_03": 0.4923,
          "f1_macro_02": 0.9846,
          "f1_weighted": 0.9846,
          "accuracy": 0.9697,
          "mae": 0.4242,
          "qwk": 0.0
        },
        {
          "fold": 2,
          "test_subject": "SUB05",
          "n_train_clips": 841,
          "n_test_clips": 52,
          "n_test_walks": 26,
          "f1_macro_03": 0.4902,
          "f1_macro_02": 0.9804,
          "f1_weighted": 0.9804,
          "accuracy": 0.9615,
          "mae": 0.4615,
          "qwk": 0.0
        },
        {
          "fold": 3,
          "test_subject": "SUB01",
          "n_train_clips": 846,
          "n_test_clips": 47,
          "n_test_walks": 40,
          "f1_macro_03": 0.0317,
          "f1_macro_02": 0.0952,
          "f1_weighted": 0.0952,
          "accuracy": 0.05,
          "mae": 1.375,
          "qwk": 0.0
        },
        {
          "fold": 4,
          "test_subject": "SUB11",
          "n_train_clips": 849,
          "n_test_clips": 44,
          "n_test_walks": 40,
          "f1_macro_03": 0.1667,
          "f1_macro_02": 0.25,
          "f1_weighted": 0.25,
          "accuracy": 0.2,
          "mae": 0.9,
          "qwk": 0.04
        },
        {
          "fold": 5,
          "test_subject": "SUB08",
          "n_train_clips": 850,
          "n_test_clips": 43,
          "n_test_walks": 43,
          "f1_macro_03": 0.2793,
          "f1_macro_02": 0.8378,
          "f1_weighted": 0.8378,
          "accuracy": 0.7209,
          "mae": 0.4186,
          "qwk": 0.0
        },
        {
          "fold": 6,
          "test_subject": "SUB14",
          "n_train_clips": 851,
          "n_test_clips": 42,
          "n_test_walks": 42,
          "f1_macro_03": 0.494,
          "f1_macro_02": 0.988,
          "f1_weighted": 0.988,
          "accuracy": 0.9762,
          "mae": 0.3095,
          "qwk": 0.0
        },
        {
          "fold": 7,
          "test_subject": "SUB06",
          "n_train_clips": 852,
          "n_test_clips": 41,
          "n_test_walks": 41,
          "f1_macro_03": 0.12,
          "f1_macro_02": 0.36,
          "f1_weighted": 0.36,
          "accuracy": 0.2195,
          "mae": 0.5366,
          "qwk": 0.0
        },
        {
          "fold": 8,
          "test_subject": "SUB16",
          "n_train_clips": 853,
          "n_test_clips": 40,
          "n_test_walks": 40,
          "f1_macro_03": 0.4872,
          "f1_macro_02": 0.9744,
          "f1_weighted": 0.9744,
          "accuracy": 0.95,
          "mae": 0.275,
          "qwk": 0.0
        },
        {
          "fold": 9,
          "test_subject": "SUB03",
          "n_train_clips": 853,
          "n_test_clips": 40,
          "n_test_walks": 40,
          "f1_macro_03": 0.2687,
          "f1_macro_02": 0.806,
          "f1_weighted": 0.806,
          "accuracy": 0.675,
          "mae": 0.65,
          "qwk": 0.0
        },
        {
          "fold": 10,
          "test_subject": "SUB19",
          "n_train_clips": 853,
          "n_test_clips": 40,
          "n_test_walks": 40,
          "f1_macro_03": 0.1333,
          "f1_macro_02": 0.4,
          "f1_weighted": 0.4,
          "accuracy": 0.25,
          "mae": 0.575,
          "qwk": 0.0
        },
        {
          "fold": 11,
          "test_subject": "SUB18",
          "n_train_clips": 853,
          "n_test_clips": 40,
          "n_test_walks": 40,
          "f1_macro_03": 0.5635,
          "f1_macro_02": 0.8452,
          "f1_weighted": 0.8452,
          "accuracy": 0.825,
          "mae": 0.35,
          "qwk": 0.6111
        },
        {
          "fold": 12,
          "test_subject": "SUB17",
          "n_train_clips": 855,
          "n_test_clips": 38,
          "n_test_walks": 38,
          "f1_macro_03": 0.3667,
          "f1_macro_02": 0.3667,
          "f1_weighted": 0.4246,
          "accuracy": 0.5789,
          "mae": 0.5526,
          "qwk": -0.1433
        },
        {
          "fold": 13,
          "test_subject": "SUB20",
          "n_train_clips": 855,
          "n_test_clips": 38,
          "n_test_walks": 38,
          "f1_macro_03": 0.1933,
          "f1_macro_02": 0.29,
          "f1_weighted": 0.2789,
          "accuracy": 0.3421,
          "mae": 0.5263,
          "qwk": -0.0609
        },
        {
          "fold": 14,
          "test_subject": "SUB21",
          "n_train_clips": 856,
          "n_test_clips": 37,
          "n_test_walks": 37,
          "f1_macro_03": 0.5486,
          "f1_macro_02": 0.8229,
          "f1_weighted": 0.8226,
          "accuracy": 0.7568,
          "mae": 0.5946,
          "qwk": 0.335
        },
        {
          "fold": 15,
          "test_subject": "SUB12",
          "n_train_clips": 856,
          "n_test_clips": 37,
          "n_test_walks": 37,
          "f1_macro_03": 0.1762,
          "f1_macro_02": 0.2643,
          "f1_weighted": 0.2491,
          "accuracy": 0.2162,
          "mae": 1.0541,
          "qwk": -0.3221
        },
        {
          "fold": 16,
          "test_subject": "SUB02",
          "n_train_clips": 857,
          "n_test_clips": 36,
          "n_test_walks": 36,
          "f1_macro_03": 0.3238,
          "f1_macro_02": 0.9714,
          "f1_weighted": 0.9714,
          "accuracy": 0.9444,
          "mae": 0.1944,
          "qwk": 0.0
        },
        {
          "fold": 17,
          "test_subject": "SUB13",
          "n_train_clips": 857,
          "n_test_clips": 36,
          "n_test_walks": 36,
          "f1_macro_03": 0.2796,
          "f1_macro_02": 0.8387,
          "f1_weighted": 0.8387,
          "accuracy": 0.7222,
          "mae": 0.5556,
          "qwk": 0.0
        },
        {
          "fold": 18,
          "test_subject": "SUB22",
          "n_train_clips": 857,
          "n_test_clips": 36,
          "n_test_walks": 36,
          "f1_macro_03": 0.2704,
          "f1_macro_02": 0.4056,
          "f1_weighted": 0.4389,
          "accuracy": 0.5278,
          "mae": 0.8889,
          "qwk": 0.0156
        },
        {
          "fold": 19,
          "test_subject": "SUB24",
          "n_train_clips": 857,
          "n_test_clips": 36,
          "n_test_walks": 36,
          "f1_macro_03": 0.1062,
          "f1_macro_02": 0.1593,
          "f1_weighted": 0.1467,
          "accuracy": 0.0833,
          "mae": 1.0556,
          "qwk": -0.1077
        },
        {
          "fold": 20,
          "test_subject": "SUB15",
          "n_train_clips": 862,
          "n_test_clips": 31,
          "n_test_walks": 8,
          "f1_macro_03": 1.0,
          "f1_macro_02": 1.0,
          "f1_weighted": 1.0,
          "accuracy": 1.0,
          "mae": 0.5,
          "qwk": 0.0
        },
        {
          "fold": 21,
          "test_subject": "SUB23",
          "n_train_clips": 873,
          "n_test_clips": 20,
          "n_test_walks": 20,
          "f1_macro_03": 0.0,
          "f1_macro_02": 0.0,
          "f1_weighted": 0.0,
          "accuracy": 0.0,
          "mae": 0.95,
          "qwk": 0.0
        },
        {
          "fold": 22,
          "test_subject": "SUB26",
          "n_train_clips": 873,
          "n_test_clips": 20,
          "n_test_walks": 20,
          "f1_macro_03": 0.4444,
          "f1_macro_02": 0.8889,
          "f1_weighted": 0.8889,
          "accuracy": 0.8,
          "mae": 0.65,
          "qwk": 0.0
        },
        {
          "fold": 23,
          "test_subject": "SUB04",
          "n_train_clips": 881,
          "n_test_clips": 12,
          "n_test_walks": 12,
          "f1_macro_03": 0.4783,
          "f1_macro_02": 0.9565,
          "f1_weighted": 0.9565,
          "accuracy": 0.9167,
          "mae": 0.3333,
          "qwk": 0.0
        }
      ],
      "summary": {
        "f1_macro_03_mean": 0.5521,
        "f1_macro_03_std": 0.219,
        "f1_macro_02_mean": 0.5521,
        "f1_macro_02_std": 0.3405,
        "f1_weighted_mean": 0.5688,
        "f1_weighted_std": 0.3399,
        "accuracy_mean": 0.57,
        "accuracy_std": 0.3386,
        "mae_mean": 0.62,
        "mae_std": 0.2879,
        "qwk_mean": 0.3783,
        "qwk_std": 0.1643,
        "spearman_mean": 0.3982,
        "spearman_std": null
      }
    },
    "3DGait": {
      "dataset": "3DGait",
      "n_subjects": 43,
      "n_clips": 210,
      "n_folds": 43,
      "updrs_dist": {
        "0": 34,
        "1": 89,
        "2": 44,
        "3": 43
      },
      "folds": [
        {
          "fold": 1,
          "test_subject": "2",
          "n_train_clips": 194,
          "n_test_clips": 16,
          "n_test_walks": 4,
          "f1_macro_03": 0.0,
          "f1_macro_02": null,
          "f1_weighted": 0.0,
          "accuracy": 0.0,
          "mae": 1.75,
          "qwk": 0.0
        },
        {
          "fold": 2,
          "test_subject": "10",
          "n_train_clips": 198,
          "n_test_clips": 12,
          "n_test_walks": 2,
          "f1_macro_03": 1.0,
          "f1_macro_02": 1.0,
          "f1_weighted": 1.0,
          "accuracy": 1.0,
          "mae": 0.0,
          "qwk": 1.0
        },
        {
          "fold": 3,
          "test_subject": "3",
          "n_train_clips": 201,
          "n_test_clips": 9,
          "n_test_walks": 4,
          "f1_macro_03": 0.1,
          "f1_macro_02": 0.4,
          "f1_weighted": 0.4,
          "accuracy": 0.25,
          "mae": 0.5,
          "qwk": 0.0
        },
        {
          "fold": 4,
          "test_subject": "1",
          "n_train_clips": 201,
          "n_test_clips": 9,
          "n_test_walks": 4,
          "f1_macro_03": 0.2222,
          "f1_macro_02": 0.6667,
          "f1_weighted": 0.6667,
          "accuracy": 0.5,
          "mae": 1.0,
          "qwk": 0.0
        },
        {
          "fold": 5,
          "test_subject": "6",
          "n_train_clips": 202,
          "n_test_clips": 8,
          "n_test_walks": 2,
          "f1_macro_03": 0.0,
          "f1_macro_02": 0.0,
          "f1_weighted": 0.0,
          "accuracy": 0.0,
          "mae": 2.0,
          "qwk": -0.1111
        },
        {
          "fold": 6,
          "test_subject": "41",
          "n_train_clips": 202,
          "n_test_clips": 8,
          "n_test_walks": 2,
          "f1_macro_03": 1.0,
          "f1_macro_02": 1.0,
          "f1_weighted": 1.0,
          "accuracy": 1.0,
          "mae": 0.0,
          "qwk": 1.0
        },
        {
          "fold": 7,
          "test_subject": "14",
          "n_train_clips": 202,
          "n_test_clips": 8,
          "n_test_walks": 2,
          "f1_macro_03": 0.3333,
          "f1_macro_02": 0.6667,
          "f1_weighted": 0.6667,
          "accuracy": 0.5,
          "mae": 0.5,
          "qwk": 0.0
        },
        {
          "fold": 8,
          "test_subject": "19",
          "n_train_clips": 203,
          "n_test_clips": 7,
          "n_test_walks": 2,
          "f1_macro_03": 0.0,
          "f1_macro_02": null,
          "f1_weighted": 0.0,
          "accuracy": 0.0,
          "mae": 1.0,
          "qwk": 0.0
        },
        {
          "fold": 9,
          "test_subject": "22",
          "n_train_clips": 203,
          "n_test_clips": 7,
          "n_test_walks": 2,
          "f1_macro_03": 1.0,
          "f1_macro_02": null,
          "f1_weighted": 1.0,
          "accuracy": 1.0,
          "mae": 0.0,
          "qwk": null
        },
        {
          "fold": 10,
          "test_subject": "26",
          "n_train_clips": 204,
          "n_test_clips": 6,
          "n_test_walks": 2,
          "f1_macro_03": 1.0,
          "f1_macro_02": 1.0,
          "f1_weighted": 1.0,
          "accuracy": 1.0,
          "mae": 0.0,
          "qwk": null
        },
        {
          "fold": 11,
          "test_subject": "38",
          "n_train_clips": 204,
          "n_test_clips": 6,
          "n_test_walks": 2,
          "f1_macro_03": 0.3333,
          "f1_macro_02": 0.3333,
          "f1_weighted": 0.3333,
          "accuracy": 0.5,
          "mae": 1.0,
          "qwk": 0.6
        },
        {
          "fold": 12,
          "test_subject": "18",
          "n_train_clips": 204,
          "n_test_clips": 6,
          "n_test_walks": 2,
          "f1_macro_03": 0.0,
          "f1_macro_02": 0.0,
          "f1_weighted": 0.0,
          "accuracy": 0.0,
          "mae": 0.5,
          "qwk": 0.6667
        },
        {
          "fold": 13,
          "test_subject": "15",
          "n_train_clips": 205,
          "n_test_clips": 5,
          "n_test_walks": 2,
          "f1_macro_03": 0.3333,
          "f1_macro_02": 0.5,
          "f1_weighted": 0.5,
          "accuracy": 0.5,
          "mae": 0.0,
          "qwk": 1.0
        },
        {
          "fold": 14,
          "test_subject": "35",
          "n_train_clips": 205,
          "n_test_clips": 5,
          "n_test_walks": 2,
          "f1_macro_03": 0.0,
          "f1_macro_02": 0.0,
          "f1_weighted": 0.0,
          "accuracy": 0.0,
          "mae": 1.0,
          "qwk": 0.3333
        },
        {
          "fold": 15,
          "test_subject": "25",
          "n_train_clips": 205,
          "n_test_clips": 5,
          "n_test_walks": 2,
          "f1_macro_03": 1.0,
          "f1_macro_02": 1.0,
          "f1_weighted": 1.0,
          "accuracy": 1.0,
          "mae": 0.5,
          "qwk": 0.0
        },
        {
          "fold": 16,
          "test_subject": "13",
          "n_train_clips": 205,
          "n_test_clips": 5,
          "n_test_walks": 2,
          "f1_macro_03": 0.3333,
          "f1_macro_02": 0.6667,
          "f1_weighted": 0.6667,
          "accuracy": 0.5,
          "mae": 0.5,
          "qwk": 0.0
        },
        {
          "fold": 17,
          "test_subject": "12",
          "n_train_clips": 205,
          "n_test_clips": 5,
          "n_test_walks": 2,
          "f1_macro_03": 0.0,
          "f1_macro_02": 0.0,
          "f1_weighted": 0.0,
          "accuracy": 0.0,
          "mae": 0.5,
          "qwk": 0.0
        },
        {
          "fold": 18,
          "test_subject": "4",
          "n_train_clips": 205,
          "n_test_clips": 5,
          "n_test_walks": 2,
          "f1_macro_03": 0.0,
          "f1_macro_02": 0.0,
          "f1_weighted": 0.0,
          "accuracy": 0.0,
          "mae": 1.0,
          "qwk": -1.0
        },
        {
          "fold": 19,
          "test_subject": "8",
          "n_train_clips": 205,
          "n_test_clips": 5,
          "n_test_walks": 2,
          "f1_macro_03": 0.0,
          "f1_macro_02": 0.0,
          "f1_weighted": 0.0,
          "accuracy": 0.0,
          "mae": 1.0,
          "qwk": 0.0
        },
        {
          "fold": 20,
          "test_subject": "24",
          "n_train_clips": 206,
          "n_test_clips": 4,
          "n_test_walks": 2,
          "f1_macro_03": 0.0,
          "f1_macro_02": 0.0,
          "f1_weighted": 0.0,
          "accuracy": 0.0,
          "mae": 0.5,
          "qwk": 0.0
        },
        {
          "fold": 21,
          "test_subject": "32",
          "n_train_clips": 206,
          "n_test_clips": 4,
          "n_test_walks": 2,
          "f1_macro_03": 1.0,
          "f1_macro_02": 1.0,
          "f1_weighted": 1.0,
          "accuracy": 1.0,
          "mae": 0.5,
          "qwk": 0.6667
        },
        {
          "fold": 22,
          "test_subject": "21",
          "n_train_clips": 206,
          "n_test_clips": 4,
          "n_test_walks": 2,
          "f1_macro_03": 0.3333,
          "f1_macro_02": 0.6667,
          "f1_weighted": 0.6667,
          "accuracy": 0.5,
          "mae": 0.0,
          "qwk": null
        },
        {
          "fold": 23,
          "test_subject": "5",
          "n_train_clips": 206,
          "n_test_clips": 4,
          "n_test_walks": 2,
          "f1_macro_03": 0.0,
          "f1_macro_02": 0.0,
          "f1_weighted": 0.0,
          "accuracy": 0.0,
          "mae": 0.5,
          "qwk": 0.0
        },
        {
          "fold": 24,
          "test_subject": "7",
          "n_train_clips": 206,
          "n_test_clips": 4,
          "n_test_walks": 2,
          "f1_macro_03": 0.0,
          "f1_macro_02": 0.0,
          "f1_weighted": 0.0,
          "accuracy": 0.0,
          "mae": 1.0,
          "qwk": -1.0
        },
        {
          "fold": 25,
          "test_subject": "42",
          "n_train_clips": 206,
          "n_test_clips": 4,
          "n_test_walks": 2,
          "f1_macro_03": 0.3333,
          "f1_macro_02": 0.5,
          "f1_weighted": 0.5,
          "accuracy": 0.5,
          "mae": 0.5,
          "qwk": 0.0
        },
        {
          "fold": 26,
          "test_subject": "27",
          "n_train_clips": 206,
          "n_test_clips": 4,
          "n_test_walks": 2,
          "f1_macro_03": 1.0,
          "f1_macro_02": 1.0,
          "f1_weighted": 1.0,
          "accuracy": 1.0,
          "mae": 0.5,
          "qwk": 0.0
        },
        {
          "fold": 27,
          "test_subject": "34",
          "n_train_clips": 206,
          "n_test_clips": 4,
          "n_test_walks": 2,
          "f1_macro_03": 0.0,
          "f1_macro_02": 0.0,
          "f1_weighted": 0.0,
          "accuracy": 0.0,
          "mae": 0.5,
          "qwk": 0.0
        },
        {
          "fold": 28,
          "test_subject": "20",
          "n_train_clips": 206,
          "n_test_clips": 4,
          "n_test_walks": 2,
          "f1_macro_03": 0.3333,
          "f1_macro_02": 0.6667,
          "f1_weighted": 0.6667,
          "accuracy": 0.5,
          "mae": 0.0,
          "qwk": null
        },
        {
          "fold": 29,
          "test_subject": "0",
          "n_train_clips": 207,
          "n_test_clips": 3,
          "n_test_walks": 2,
          "f1_macro_03": 0.3333,
          "f1_macro_02": 0.3333,
          "f1_weighted": 0.3333,
          "accuracy": 0.5,
          "mae": 0.5,
          "qwk": 0.0
        },
        {
          "fold": 30,
          "test_subject": "9",
          "n_train_clips": 207,
          "n_test_clips": 3,
          "n_test_walks": 2,
          "f1_macro_03": 0.0,
          "f1_macro_02": 0.0,
          "f1_weighted": 0.0,
          "accuracy": 0.0,
          "mae": 0.0,
          "qwk": null
        },
        {
          "fold": 31,
          "test_subject": "16",
          "n_train_clips": 207,
          "n_test_clips": 3,
          "n_test_walks": 2,
          "f1_macro_03": 0.3333,
          "f1_macro_02": 0.3333,
          "f1_weighted": 0.3333,
          "accuracy": 0.5,
          "mae": 0.5,
          "qwk": 0.0
        },
        {
          "fold": 32,
          "test_subject": "31",
          "n_train_clips": 207,
          "n_test_clips": 3,
          "n_test_walks": 2,
          "f1_macro_03": 0.3333,
          "f1_macro_02": 0.6667,
          "f1_weighted": 0.6667,
          "accuracy": 0.5,
          "mae": 0.5,
          "qwk": 0.0
        },
        {
          "fold": 33,
          "test_subject": "30",
          "n_train_clips": 207,
          "n_test_clips": 3,
          "n_test_walks": 2,
          "f1_macro_03": 0.3333,
          "f1_macro_02": 0.6667,
          "f1_weighted": 0.6667,
          "accuracy": 0.5,
          "mae": 1.0,
          "qwk": 0.0
        },
        {
          "fold": 34,
          "test_subject": "29",
          "n_train_clips": 207,
          "n_test_clips": 3,
          "n_test_walks": 2,
          "f1_macro_03": 0.3333,
          "f1_macro_02": 0.6667,
          "f1_weighted": 0.6667,
          "accuracy": 0.5,
          "mae": 0.5,
          "qwk": 0.0
        },
        {
          "fold": 35,
          "test_subject": "33",
          "n_train_clips": 207,
          "n_test_clips": 3,
          "n_test_walks": 2,
          "f1_macro_03": 0.3333,
          "f1_macro_02": 0.3333,
          "f1_weighted": 0.3333,
          "accuracy": 0.5,
          "mae": 1.0,
          "qwk": -1.0
        },
        {
          "fold": 36,
          "test_subject": "39",
          "n_train_clips": 208,
          "n_test_clips": 2,
          "n_test_walks": 2,
          "f1_macro_03": 0.0,
          "f1_macro_02": 0.0,
          "f1_weighted": 0.0,
          "accuracy": 0.0,
          "mae": 0.5,
          "qwk": 0.0
        },
        {
          "fold": 37,
          "test_subject": "40",
          "n_train_clips": 208,
          "n_test_clips": 2,
          "n_test_walks": 2,
          "f1_macro_03": 1.0,
          "f1_macro_02": 1.0,
          "f1_weighted": 1.0,
          "accuracy": 1.0,
          "mae": 0.0,
          "qwk": null
        },
        {
          "fold": 38,
          "test_subject": "37",
          "n_train_clips": 208,
          "n_test_clips": 2,
          "n_test_walks": 2,
          "f1_macro_03": 1.0,
          "f1_macro_02": 1.0,
          "f1_weighted": 1.0,
          "accuracy": 1.0,
          "mae": 0.0,
          "qwk": null
        },
        {
          "fold": 39,
          "test_subject": "36",
          "n_train_clips": 208,
          "n_test_clips": 2,
          "n_test_walks": 2,
          "f1_macro_03": 1.0,
          "f1_macro_02": 1.0,
          "f1_weighted": 1.0,
          "accuracy": 1.0,
          "mae": 1.0,
          "qwk": 0.0
        },
        {
          "fold": 40,
          "test_subject": "23",
          "n_train_clips": 208,
          "n_test_clips": 2,
          "n_test_walks": 2,
          "f1_macro_03": 0.3333,
          "f1_macro_02": 0.6667,
          "f1_weighted": 0.6667,
          "accuracy": 0.5,
          "mae": 0.5,
          "qwk": 0.0
        },
        {
          "fold": 41,
          "test_subject": "28",
          "n_train_clips": 208,
          "n_test_clips": 2,
          "n_test_walks": 1,
          "f1_macro_03": 0.0,
          "f1_macro_02": 0.0,
          "f1_weighted": 0.0,
          "accuracy": 0.0,
          "mae": 0.0,
          "qwk": null
        },
        {
          "fold": 42,
          "test_subject": "17",
          "n_train_clips": 208,
          "n_test_clips": 2,
          "n_test_walks": 2,
          "f1_macro_03": 1.0,
          "f1_macro_02": 1.0,
          "f1_weighted": 1.0,
          "accuracy": 1.0,
          "mae": 0.0,
          "qwk": null
        },
        {
          "fold": 43,
          "test_subject": "11",
          "n_train_clips": 208,
          "n_test_clips": 2,
          "n_test_walks": 1,
          "f1_macro_03": 1.0,
          "f1_macro_02": 1.0,
          "f1_weighted": 1.0,
          "accuracy": 1.0,
          "mae": 1.0,
          "qwk": 0.0
        }
      ],
      "summary": {
        "f1_macro_03_mean": 0.4449,
        "f1_macro_03_std": 0.4007,
        "f1_macro_02_mean": 0.4599,
        "f1_macro_02_std": 0.399,
        "f1_weighted_mean": 0.4446,
        "f1_weighted_std": 0.4066,
        "accuracy_mean": 0.4444,
        "accuracy_std": 0.3959,
        "mae_mean": 0.5889,
        "mae_std": 0.4687,
        "qwk_mean": 0.5129,
        "qwk_std": 0.4613,
        "spearman_mean": 0.5879,
        "spearman_std": null
      }
    },
    "T-SDU-PD": {
      "dataset": "T-SDU-PD",
      "n_subjects": 14,
      "n_clips": 931,
      "n_folds": 14,
      "updrs_dist": {
        "0": 179,
        "1": 267,
        "2": 485
      },
      "folds": [
        {
          "fold": 1,
          "test_subject": "P008",
          "n_train_clips": 792,
          "n_test_clips": 139,
          "n_test_walks": 58,
          "f1_macro_03": 0.2395,
          "f1_macro_02": 0.3593,
          "f1_weighted": 0.4077,
          "accuracy": 0.3276,
          "mae": 0.8966,
          "qwk": 0.023
        },
        {
          "fold": 2,
          "test_subject": "P004",
          "n_train_clips": 815,
          "n_test_clips": 116,
          "n_test_walks": 51,
          "f1_macro_03": 0.2903,
          "f1_macro_02": 0.4355,
          "f1_weighted": 0.4997,
          "accuracy": 0.4314,
          "mae": 0.7059,
          "qwk": 0.023
        },
        {
          "fold": 3,
          "test_subject": "P007",
          "n_train_clips": 841,
          "n_test_clips": 90,
          "n_test_walks": 42,
          "f1_macro_03": 0.2672,
          "f1_macro_02": 0.4008,
          "f1_weighted": 0.4184,
          "accuracy": 0.381,
          "mae": 0.619,
          "qwk": 0.1091
        },
        {
          "fold": 4,
          "test_subject": "P006",
          "n_train_clips": 842,
          "n_test_clips": 89,
          "n_test_walks": 21,
          "f1_macro_03": 0.4615,
          "f1_macro_02": 0.9231,
          "f1_weighted": 0.9231,
          "accuracy": 0.8571,
          "mae": 0.5238,
          "qwk": 0.0
        },
        {
          "fold": 5,
          "test_subject": "P009",
          "n_train_clips": 843,
          "n_test_clips": 88,
          "n_test_walks": 31,
          "f1_macro_03": 0.1404,
          "f1_macro_02": 0.2105,
          "f1_weighted": 0.3803,
          "accuracy": 0.2581,
          "mae": 0.6129,
          "qwk": 0.0061
        },
        {
          "fold": 6,
          "test_subject": "P012",
          "n_train_clips": 865,
          "n_test_clips": 66,
          "n_test_walks": 35,
          "f1_macro_03": 0.1481,
          "f1_macro_02": 0.4444,
          "f1_weighted": 0.4444,
          "accuracy": 0.2857,
          "mae": 1.0571,
          "qwk": 0.0
        },
        {
          "fold": 7,
          "test_subject": "P011",
          "n_train_clips": 865,
          "n_test_clips": 66,
          "n_test_walks": 29,
          "f1_macro_03": 0.1653,
          "f1_macro_02": 0.2479,
          "f1_weighted": 0.3457,
          "accuracy": 0.2414,
          "mae": 0.3103,
          "qwk": 0.0
        },
        {
          "fold": 8,
          "test_subject": "P013",
          "n_train_clips": 871,
          "n_test_clips": 60,
          "n_test_walks": 26,
          "f1_macro_03": 0.4233,
          "f1_macro_02": 0.6349,
          "f1_weighted": 0.6593,
          "accuracy": 0.5769,
          "mae": 0.3846,
          "qwk": 0.2744
        },
        {
          "fold": 9,
          "test_subject": "P005",
          "n_train_clips": 872,
          "n_test_clips": 59,
          "n_test_walks": 26,
          "f1_macro_03": 0.0926,
          "f1_macro_02": 0.1389,
          "f1_weighted": 0.1346,
          "accuracy": 0.0769,
          "mae": 1.1154,
          "qwk": 0.073
        },
        {
          "fold": 10,
          "test_subject": "P002",
          "n_train_clips": 881,
          "n_test_clips": 50,
          "n_test_walks": 9,
          "f1_macro_03": 1.0,
          "f1_macro_02": 1.0,
          "f1_weighted": 1.0,
          "accuracy": 1.0,
          "mae": 0.5556,
          "qwk": 0.0
        },
        {
          "fold": 11,
          "test_subject": "P010",
          "n_train_clips": 890,
          "n_test_clips": 41,
          "n_test_walks": 21,
          "f1_macro_03": 0.2,
          "f1_macro_02": 0.6,
          "f1_weighted": 0.6,
          "accuracy": 0.4286,
          "mae": 0.8571,
          "qwk": 0.0
        },
        {
          "fold": 12,
          "test_subject": "P014",
          "n_train_clips": 890,
          "n_test_clips": 41,
          "n_test_walks": 20,
          "f1_macro_03": 0.35,
          "f1_macro_02": 0.525,
          "f1_weighted": 0.69,
          "accuracy": 0.65,
          "mae": 0.75,
          "qwk": 0.0
        },
        {
          "fold": 13,
          "test_subject": "P003",
          "n_train_clips": 907,
          "n_test_clips": 24,
          "n_test_walks": 11,
          "f1_macro_03": 0.3778,
          "f1_macro_02": 0.5667,
          "f1_weighted": 0.6303,
          "accuracy": 0.6364,
          "mae": 0.4545,
          "qwk": 0.1538
        },
        {
          "fold": 14,
          "test_subject": "P001",
          "n_train_clips": 929,
          "n_test_clips": 2,
          "n_test_walks": 1,
          "f1_macro_03": 1.0,
          "f1_macro_02": 1.0,
          "f1_weighted": 1.0,
          "accuracy": 1.0,
          "mae": 0.0,
          "qwk": null
        }
      ],
      "summary": {
        "f1_macro_03_mean": 0.401,
        "f1_macro_03_std": 0.2789,
        "f1_macro_02_mean": 0.401,
        "f1_macro_02_std": 0.2686,
        "f1_weighted_mean": 0.4205,
        "f1_weighted_std": 0.2487,
        "accuracy_mean": 0.4094,
        "accuracy_std": 0.2774,
        "mae_mean": 0.7139,
        "mae_std": 0.2889,
        "qwk_mean": 0.2129,
        "qwk_std": 0.0802,
        "spearman_mean": 0.3253,
        "spearman_std": null
      }
    }
  }
}